qubitcooling/__init__.py
qubitcooling/coolingCircuit.py
qubitcooling/coolingUnitary.py
qubitcooling/dynamicCooling.py
qubitcooling/heatBathCooling.py
qubitcooling/minimalWorkProtocol.py
qubitcooling/mirrorProtocol.py
qubitcooling/partnerPairingAlgorithm.py
qubitcooling/semiOpenCooling.py
qubitcooling/subOptimalCooling.py
qubitcooling/utils/occupationProbabilitiesList.py
qubitcooling/utils/testCircuit.py
qubitcooling/utils/utils.py
qubitcooling-1.dist-info/licenses/LICENSE
qubitcooling-1.dist-info/METADATA
qubitcooling-1.dist-info/WHEEL
qubitcooling-1.dist-info/top_level.txt
qubitcooling-1.dist-info/RECORD
